{
  "pitcher_id": "621112",
  "name": "Paul Blackburn",
  "hand": "R",
  "pitch_mix": {
    "SI": 0.2415,
    "FC": 0.2015,
    "ST": 0.1744,
    "FF": 0.1421,
    "CU": 0.1128,
    "CH": 0.1108
  },
  "primary_pitch": "SI",
  "zone_map": {
    "14": 0.2759,
    "13": 0.1092,
    "12": 0.0944,
    "11": 0.0764,
    "6": 0.0682,
    "9": 0.0626,
    "5": 0.0595,
    "8": 0.0492,
    "3": 0.0487,
    "4": 0.0436,
    "7": 0.0364,
    "2": 0.0323,
    "1": 0.0267,
    "out_of_zone": 0.5559
  },
  "preferred_zones": [
    "6",
    "9",
    "5"
  ],
  "bb_pct": 0.09,
  "chase_rate": 0.3062,
  "whiff_rate": 0.2282,
  "k_pct": 0.2229,
  "vs_lhh_splits": {
    "pitch_mix": {
      "FC": 0.2236,
      "CH": 0.2083,
      "SI": 0.1799,
      "CU": 0.1614,
      "FF": 0.1254,
      "ST": 0.0829
    },
    "zone_map": {
      "14": 0.2017,
      "13": 0.1418,
      "11": 0.1003,
      "12": 0.0971,
      "5": 0.0632,
      "6": 0.0556,
      "8": 0.0556,
      "4": 0.0545,
      "3": 0.0545,
      "7": 0.048,
      "9": 0.0425,
      "2": 0.036,
      "1": 0.0305,
      "out_of_zone": 0.5409
    }
  },
  "vs_rhh_splits": {
    "pitch_mix": {
      "SI": 0.2962,
      "ST": 0.2556,
      "FC": 0.182,
      "FF": 0.1568,
      "CU": 0.0697,
      "CH": 0.0242
    },
    "zone_map": {
      "14": 0.3417,
      "12": 0.092,
      "9": 0.0803,
      "13": 0.0803,
      "6": 0.0794,
      "5": 0.0561,
      "11": 0.0552,
      "3": 0.0436,
      "8": 0.0436,
      "4": 0.0339,
      "2": 0.029,
      "7": 0.0261,
      "1": 0.0232,
      "out_of_zone": 0.5692
    }
  },
  "sample_size": 1950,
  "last_updated": "2026-04-14",
  "data_source": "backtest_prior_season"
}