{
  "vulnerable_zones": [
    "4",
    "7",
    "2"
  ],
  "chase_rate": 0.3154,
  "contact_rate": 0.6852,
  "name": "",
  "zone_cold_spots": {
    "2": 0.0,
    "9": 0.3638,
    "4": 0.0,
    "7": 0.321,
    "1": 0.202
  },
  "preferred_hit_zones": [
    "8",
    "9",
    "5"
  ],
  "pitch_type_perf": {
    "SL": 0.3538,
    "KC": 0.3973,
    "SI": 0.4447,
    "CU": 0.3553,
    "ST": 0.3372,
    "FC": 0.3427,
    "FS": 0.2633,
    "FF": 0.4351,
    "CH": 0.4021
  },
  "bb_pct": 0.1381,
  "batter_id": "547180",
  "worst_pitch_type": "CU",
  "k_pct": 0.2163,
  "best_pitch_type": "ST",
  "hand": "L",
  "zone_hot_spots": {
    "2": 0.5768,
    "9": 0.0,
    "5": 0.5736,
    "4": 0.592,
    "8": 0.0
  },
  "data_source": "backtest_blended",
  "sample_size": 746,
  "current_season_pitches": 145,
  "last_updated": "2026-04-14"
}