{
  "vulnerable_zones": [
    "9",
    "8",
    "4"
  ],
  "chase_rate": 0.2472,
  "contact_rate": 0.8016,
  "name": "",
  "zone_cold_spots": {
    "9": 0.0,
    "4": 0.0,
    "8": 0.0,
    "7": 0.3373,
    "1": 0.1617,
    "3": 0.3079
  },
  "preferred_hit_zones": [
    "5",
    "6",
    "7"
  ],
  "pitch_type_perf": {
    "KC": 0.2444,
    "SL": 0.3257,
    "SI": 0.4106,
    "CU": 0.2661,
    "FC": 0.5264,
    "ST": 0.1753,
    "FS": 0.1173,
    "FF": 0.3792,
    "CH": 0.3383
  },
  "bb_pct": 0.0911,
  "batter_id": "596146",
  "worst_pitch_type": "CH",
  "k_pct": 0.2204,
  "best_pitch_type": "FC",
  "hand": "L",
  "zone_hot_spots": {
    "2": 0.455,
    "9": 0.505,
    "5": 0.433,
    "7": 0.0,
    "6": 0.0
  },
  "data_source": "backtest_blended",
  "sample_size": 679,
  "current_season_pitches": 130,
  "last_updated": "2026-04-14"
}