{
  "batter_id": "664913",
  "name": "",
  "hand": "L",
  "zone_hot_spots": {
    "4": 0.5903,
    "1": 0.4242,
    "5": 0.3664
  },
  "zone_cold_spots": {
    "6": 0.2909,
    "3": 0.2757,
    "7": 0.1866
  },
  "preferred_hit_zones": [
    "4",
    "1",
    "5"
  ],
  "vulnerable_zones": [
    "6",
    "3",
    "7"
  ],
  "pitch_type_perf": {
    "ST": 0.3083,
    "FF": 0.3125,
    "CH": 0.2101,
    "SL": 0.2083,
    "SI": 0.3225,
    "FS": 0.3718,
    "FC": 0.4224,
    "CU": 0.2559,
    "KC": 0.826
  },
  "best_pitch_type": "KC",
  "worst_pitch_type": "SL",
  "bb_pct": 0.0769,
  "k_pct": 0.2668,
  "chase_rate": 0.3398,
  "contact_rate": 0.6959,
  "sample_size": 416,
  "last_updated": "2026-04-14",
  "data_source": "backtest_prior_season"
}