{
  "bb_pct": 0.1481,
  "k_pct": 0.3202,
  "vulnerable_zones": [
    "7",
    "9",
    "1"
  ],
  "zone_cold_spots": {
    "9": 0.1276,
    "3": 0.1843,
    "7": 0.2546,
    "1": 0.0
  },
  "best_pitch_type": "FF",
  "batter_id": "666397",
  "preferred_hit_zones": [
    "2",
    "6",
    "5"
  ],
  "pitch_type_perf": {
    "KC": 0.2522,
    "FF": 0.4626,
    "SI": 0.2979,
    "CH": 0.3213,
    "ST": 0.1549,
    "SL": 0.314,
    "CU": 0.2303,
    "FS": 0.1554,
    "FC": 0.3783
  },
  "zone_hot_spots": {
    "2": 0.1685,
    "5": 0.4411,
    "1": 0.3118,
    "6": 0.4848
  },
  "chase_rate": 0.1582,
  "contact_rate": 0.7223,
  "name": "",
  "hand": "L",
  "worst_pitch_type": "CU",
  "data_source": "backtest_blended",
  "sample_size": 740,
  "current_season_pitches": 294,
  "last_updated": "2026-04-15"
}