{
  "bb_pct": 0.1046,
  "k_pct": 0.2683,
  "vulnerable_zones": [
    "9",
    "1",
    "6"
  ],
  "zone_cold_spots": {
    "6": 0.0,
    "4": 0.161,
    "1": 0.0189,
    "3": 0.1502,
    "9": 0.0587,
    "7": 0.1663
  },
  "best_pitch_type": "CH",
  "batter_id": "573262",
  "preferred_hit_zones": [
    "8",
    "3",
    "4"
  ],
  "pitch_type_perf": {
    "FF": 0.3478,
    "SI": 0.308,
    "CH": 0.3682,
    "SL": 0.1201,
    "ST": 0.2263,
    "CU": 0.6186,
    "FS": 0.4372,
    "FC": 0.3314
  },
  "zone_hot_spots": {
    "2": 0.378,
    "8": 0.4453,
    "4": 0.1099,
    "3": 0.174,
    "5": 0.3399
  },
  "chase_rate": 0.2257,
  "contact_rate": 0.7711,
  "name": "",
  "hand": "L",
  "worst_pitch_type": "ST",
  "data_source": "backtest_blended",
  "sample_size": 630,
  "current_season_pitches": 221,
  "last_updated": "2026-04-15"
}