{
  "bb_pct": 0.1262,
  "k_pct": 0.1563,
  "vulnerable_zones": [
    "8",
    "7",
    "4"
  ],
  "zone_cold_spots": {
    "8": 0.1652,
    "4": 0.0845,
    "3": 0.0704,
    "9": 0.0704,
    "7": 0.178
  },
  "best_pitch_type": "SL",
  "batter_id": "694384",
  "preferred_hit_zones": [
    "5",
    "3",
    "9"
  ],
  "pitch_type_perf": {
    "KC": 0.0,
    "FF": 0.3608,
    "SI": 0.3056,
    "CH": 0.3501,
    "SL": 0.2993,
    "ST": 0.3222,
    "CU": 0.2811,
    "FS": 0.1006,
    "FC": 0.3719
  },
  "zone_hot_spots": {
    "2": 0.1724,
    "8": 0.1903,
    "6": 0.202,
    "3": 0.2687,
    "5": 0.275,
    "9": 0.2446
  },
  "chase_rate": 0.221,
  "contact_rate": 0.8578,
  "name": "",
  "hand": "L",
  "worst_pitch_type": "KC",
  "data_source": "backtest_blended",
  "sample_size": 750,
  "current_season_pitches": 617,
  "last_updated": "2026-04-15"
}